ezkl_lib-0.3.0.dist-info/METADATA
ezkl_lib-0.3.0.dist-info/WHEEL
ezkl_lib-0.3.0.dist-info/license_files/LICENSE
ezkl_lib/__init__.py
ezkl_lib/ezkl_lib.abi3.so
ezkl_lib-0.3.0.dist-info/RECORD
